{"cameraMode":{"drawMode":0,"name":"Shaded","section":"Shading Mode"},"sceneLighting":true,"audioPlay":false,"sceneViewState":{"showFog":true,"showMaterialUpdate":false,"showSkybox":true,"showFlares":true,"showImageEffects":true,"showParticleSystems":true},"in2DMode":false,"pivot":{"x":0.7869192957878113,"y":0.7463918924331665,"z":0.08728063851594925},"rotation":{"x":-0.058922454714775088,"y":0.9410164952278137,"z":-0.24109290540218354,"w":-0.22998233139514924},"size":6.728954315185547,"orthographic":false}